LICENSE
MANIFEST.in
README.md
requirements.txt
setup.py
CodeShow.egg-info/PKG-INFO
CodeShow.egg-info/SOURCES.txt
CodeShow.egg-info/dependency_links.txt
CodeShow.egg-info/entry_points.txt
CodeShow.egg-info/requires.txt
CodeShow.egg-info/top_level.txt
codeshow/__init__.py
codeshow/cmdline.py
codeshow/format.py
codeshow/util.py
codeshow/templates/bottom
codeshow/templates/css
codeshow/templates/directory
codeshow/templates/top