Metadata-Version: 1.0
Name: CodeShow
Version: 0.2.2
Summary: CodeShow turns a directory of code into a static website suitable for use in presentations.
Home-page: http://codeshow.site44.com
Author: Steve Marx
Author-email: smarx@smarx.com
License: Copyright (C) 2012 Steve Marx
